setup.py
radishsalad/__init__.py
radishsalad/connection.py
radishsalad/datatypes.py
radishsalad/models.py
radishsalad.egg-info/PKG-INFO
radishsalad.egg-info/SOURCES.txt
radishsalad.egg-info/dependency_links.txt
radishsalad.egg-info/requires.txt
radishsalad.egg-info/top_level.txt