Metadata-Version: 1.0
Name: radishsalad
Version: 0.1.0
Summary: Redis datastore library
Home-page: https://github.com/Deepwalker/radishsalad/
Author: Mikhail Krivushin
Author-email: krivushinme@gmail.com
License: BSD
Platform: UNKNOWN
Classifier: Intended Audience :: Developers
Classifier: License :: OSI Approved :: BSD License
Classifier: Operating System :: OS Independent
Classifier: Programming Language :: Python
